tumdlr/__init__.py
tumdlr/api.py
tumdlr/config.py
tumdlr/containers.py
tumdlr/downloader.py
tumdlr/errors.py
tumdlr/main.py
tumdlr/commands/__init__.py
tumdlr/commands/download.py
tumdlr/commands/setup.py
tumdlr/data/TERMS.rst
tumdlr/data/config/tumdlr.cfg
tumdlr/data/config/tumdlr.cfg.example
tumdlr/database/__init__.py
tumdlr/database/models.py
tumdlr/database/setup.py
tumdlr-0.2.0.dist-info/DESCRIPTION.rst
tumdlr-0.2.0.dist-info/METADATA
tumdlr-0.2.0.dist-info/RECORD
tumdlr-0.2.0.dist-info/WHEEL
tumdlr-0.2.0.dist-info/entry_points.txt
tumdlr-0.2.0.dist-info/metadata.json
tumdlr-0.2.0.dist-info/top_level.txt
