Metadata-Version: 2.0
Name: tumdlr
Version: 0.2.0
Summary: A Tumblr image and video scraping utility
Home-page: https://github.com/FujiMakoto/tumdlr/tree/master
Author: makoto
Author-email: makoto@makoto.io
License: MIT
Keywords: tumblr scraper downloader youtube-dl
Platform: UNKNOWN
Classifier: Development Status :: 2 - Pre-Alpha
Classifier: License :: OSI Approved :: MIT License
Classifier: Environment :: Console
Classifier: Intended Audience :: End Users/Desktop
Classifier: Natural Language :: English
Classifier: Topic :: Internet :: WWW/HTTP
Classifier: Topic :: System :: Archiving
Classifier: Topic :: System :: Archiving :: Mirroring
Classifier: Topic :: Utilities
Classifier: Programming Language :: Python :: 3.4
Classifier: Programming Language :: Python :: 3.5
Requires-Dist: appdirs
Requires-Dist: click
Requires-Dist: humanize
Requires-Dist: lxml
Requires-Dist: requests
Requires-Dist: youtube-dl
Requires-Dist: yurl
